README.md
setup.py
dr/__main__.py
dr/commandeler.py
dr/commands.py
dr/globals.py
dr/specall.py
dr.egg-info/PKG-INFO
dr.egg-info/SOURCES.txt
dr.egg-info/dependency_links.txt
dr.egg-info/entry_points.txt
dr.egg-info/requires.txt
dr.egg-info/top_level.txt