Metadata-Version: 2.1
Name: dr
Version: 1.9.3
Summary: An ed-like devRant client
Home-page: https://github.com/Ewpratten/dr
Author: Evan Pratten
Author-email: ewpratten@gmail.com
License: UNKNOWN
Platform: UNKNOWN
Classifier: Programming Language :: Python :: 3
Classifier: Operating System :: OS Independent
Classifier: Development Status :: 5 - Production/Stable
